pyi18n_new/__init__.py
pyi18n_new/i18n.py
pyi18n_new/lib/base_class.py
pyi18n_new/lib/prettyword.py
pyi18n_new/models/locale.py
pyi18n_new/models/section.py
pyi18n_new/models/value.py
pyi18n_new-1.1.0.post2.dist-info/LICENSE
pyi18n_new-1.1.0.post2.dist-info/METADATA
pyi18n_new-1.1.0.post2.dist-info/WHEEL
pyi18n_new-1.1.0.post2.dist-info/RECORD
