Metadata-Version: 2.1
Name: pyi18n_new
Version: 1.1.0.post2
Summary: Advanced i18n realization
License: MIT
Author: Daniel Zakharov
Author-email: gzdan734@gmail.com
Requires-Python: >=3.10,<4.0
Classifier: License :: OSI Approved :: MIT License
Classifier: Programming Language :: Python :: 3
Classifier: Programming Language :: Python :: 3.10
Classifier: Programming Language :: Python :: 3.11
Classifier: Programming Language :: Python :: 3.12
Requires-Dist: PyYAML (>=6.0,<7.0)
Requires-Dist: pydantic (>=2.6.3,<3.0.0)
